<?xml version="1.0" encoding="UTF-8"?>
<ti:app 
  xmlns:ti="http://ti.appcelerator.org">
  <id>com.eventrize</id>
  <name>eventrize</name>
  <version>2.0</version>
  <publisher>Rize Innovations</publisher>
  <url>http://eventrize.com</url>
  <description>not specified</description>
  <copyright>2015 Rize Innovations</copyright>
  <icon>appicon.png</icon>
  <fullscreen>false</fullscreen>
  <navbar-hidden>false</navbar-hidden>
  <analytics>false</analytics>
  <guid>ae45f844-6916-44df-9000-93a1ff2bc0f2</guid>
  <property name="ti.ui.defaultunit" type="string">dp</property>
  <ios>
    <plist>
      <dict>
        <key>UISupportedInterfaceOrientations~iphone</key>
        <array>
          <string>UIInterfaceOrientationPortrait</string>
        </array>
        <key>UISupportedInterfaceOrientations~ipad</key>
        <array>
          <string>UIInterfaceOrientationPortrait</string>
          <string>UIInterfaceOrientationPortraitUpsideDown</string>
          <string>UIInterfaceOrientationLandscapeLeft</string>
          <string>UIInterfaceOrientationLandscapeRight</string>
        </array>
        <key>UIRequiresPersistentWiFi</key>
        <false/>
        <key>UIPrerenderedIcon</key>
        <false/>
        <key>UIStatusBarHidden</key>
        <false/>
        <key>UIStatusBarStyle</key>
        <string>UIStatusBarStyleDefault</string>
      </dict>
    </plist>
  </ios>
  <android
    xmlns:android="http://schemas.android.com/apk/res/android">
    <manifest android:versionCode="1" android:versionName="1">
      <application android:theme="@style/AppTheme"/>
    </manifest>
  </android>
  <modules>
    <module platform="android" version="0.6">com.rkam.swiperefreshlayout</module>
    <module platform="iphone" version="1.8.2">dk.napp.social</module>
    <module platform="iphone" version="2.5.0">ti.map</module>
    <module platform="android" version="2.3.6">ti.map</module>
    <module platform="commonjs" version="0.1.2">ti-push-notification</module>
    <module platform="android" version="1.3">nl.vanvianen.android.gcm</module>
    <module platform="iphone" version="1.1.1">dk.napp.imageview</module>
    <module platform="iphone" version="0.2">com.shareourideas.locale</module>
    <module platform="android" version="0.1">com.shareourideas.locale</module>
  </modules>
  <deployment-targets>
    <target device="android">true</target>
    <target device="ipad">false</target>
    <target device="iphone">true</target>
    <target device="mobileweb">false</target>
    <target device="windows">false</target>
  </deployment-targets>
  <sdk-version>5.1.0.GA</sdk-version>
  <plugins>
    <plugin version="1.0">ti.alloy</plugin>
  </plugins>
  <property name="appc-app-id" type="string">564db70c577e33b53e75c683</property>
</ti:app>